compilerinterface/BaseCompilerInterface.py
compilerinterface/GrpcCompilerInterface.py
compilerinterface/PipeCompilerInterface.py
compilerinterface/SerDes.py
compilerinterface/__init__.py
compilerinterface/log_reader.py
compilerinterface-0.0.2.dist-info/METADATA
compilerinterface-0.0.2.dist-info/WHEEL
compilerinterface-0.0.2.dist-info/top_level.txt
compilerinterface-0.0.2.dist-info/RECORD
