Metadata-Version: 2.1
Name: compilerinterface
Version: 0.0.2
Summary: Communication framework for ML-Enabled Compiler Optimizations.
Home-page: https://github.com/IITH-Compilers/ML-Compiler-Bridge/
Author: The authors of "The Next 700 ML-Enabled Compiler Optimizations"
License: Apache License v2.0 with LLVM Exceptions
Classifier: Programming Language :: Python :: 3
Classifier: Programming Language :: Python :: 3.7
Classifier: Programming Language :: Python :: 3.8
Classifier: Programming Language :: Python :: 3.9
Classifier: Programming Language :: Python :: 3.10
Classifier: Programming Language :: Python :: 3.11
Classifier: Intended Audience :: Developers
Classifier: Intended Audience :: Science/Research
Classifier: Topic :: Scientific/Engineering :: Artificial Intelligence
Classifier: Topic :: Software Development :: Compilers
Classifier: Development Status :: 4 - Beta
Classifier: Operating System :: POSIX :: Linux
Requires-Python: >=3.7
